aporia/__init__.py
aporia/as_code/__init__.py
aporia/as_code/resources/base.py
aporia/as_code/resources/custom_metrics.py
aporia/as_code/resources/data_source.py
aporia/as_code/resources/dataset.py
aporia/as_code/resources/model.py
aporia/as_code/resources/monitor.py
aporia/as_code/resources/segment.py
aporia/as_code/resources/version.py
aporia/as_code/stack.py
aporia/sdk/__init__.py
aporia/sdk/aporia_api.py
aporia/sdk/base.py
aporia/sdk/client.py
aporia/sdk/custom_metrics.py
aporia/sdk/dashboards.py
aporia/sdk/data_sources.py
aporia/sdk/datasets.py
aporia/sdk/fields.py
aporia/sdk/messaging.py
aporia/sdk/metrics.py
aporia/sdk/models.py
aporia/sdk/monitors.py
aporia/sdk/segments.py
aporia/sdk/versions.py
aporia/sdk/widgets/__init__.py
aporia/sdk/widgets/base.py
aporia/sdk/widgets/data_health_table_widget.py
aporia/sdk/widgets/distribution_widget.py
aporia/sdk/widgets/histogram_over_time_widget.py
aporia/sdk/widgets/metric_by_segment_widget.py
aporia/sdk/widgets/metric_correlation_widget.py
aporia/sdk/widgets/metric_widget.py
aporia/sdk/widgets/text_widget.py
aporia/sdk/widgets/timeseries_widget.py
aporia-3.38.0.dist-info/METADATA
aporia-3.38.0.dist-info/WHEEL
aporia-3.38.0.dist-info/RECORD
