Metadata-Version: 2.3
Name: aporia
Version: 3.38.0
Summary: 
Author: Aporia
Author-email: support@aporia.com
Requires-Python: >=3.8,<4.0
Classifier: Programming Language :: Python :: 3
Classifier: Programming Language :: Python :: 3.8
Classifier: Programming Language :: Python :: 3.9
Classifier: Programming Language :: Python :: 3.10
Classifier: Programming Language :: Python :: 3.11
Classifier: Programming Language :: Python :: 3.12
Classifier: Programming Language :: Python :: 3.13
Requires-Dist: pydantic (>=1.10,<2.0)
Requires-Dist: requests (>=2.28,<3.0)
